<?xml version="1.0" encoding="utf-8"?>
<resources>
    <string-array name="additional_repos">
        <!-- name -->
        <item>Bromite F-Droid repo</item>
        <!-- address -->
        <item>https://fdroid.bromite.org/fdroid/repo</item>
        <!-- description -->
        <item>This is a repository of microG apps to be used with F-Droid. Applications in this repository are signed official binaries built by the microG Team from the corresponding source code.</item>
        <!-- version -->
        <item>19</item>
        <!-- enabled -->
        <item>1</item>
        <!-- push requests -->
        <item>ignore</item>
        <!-- pubkey -->
        <item>E1EE5CD076D7B0DC84CB2B45FB78B86DF2EB39A3B6C56BA3DC292A5E0C3B9504</item>

    </string-array>
</resources>
